{
  "354": {
    "name": "354",
    "observations": "a large fraction of this are answers that are a in dm math",
    "lastModified": "2025-10-16T20:02:34.701Z",
    "author": "github-user"
  },
  "358": {
    "name": "358",
    "observations": "dm math answers that are false",
    "lastModified": "2025-10-16T20:01:18.332Z",
    "author": "github-user"
  },
  "359": {
    "name": "359",
    "observations": "reasonable number of numbers",
    "lastModified": "2025-10-16T20:01:00.676Z",
    "author": "github-user"
  }
}